[
 {
  "body": "https://www.geeksforgeeks.org/type-conversion-in-python/",
  "chapter": "0001 Python",
  "content": null,
  "course": "industrial-training",
  "custom_content_copy": null,
  "docstatus": 0,
  "doctype": "Course Lesson",
  "file_type": "",
  "include_in_preview": 1,
  "index_label": null,
  "instructor_content": null,
  "instructor_notes": null,
  "modified": "2024-06-05 12:32:58.565242",
  "name": "0007 Data Type Conversion",
  "question": null,
  "quiz_id": null,
  "title": "Data Type Conversion",
  "youtube": null
 },
 {
  "body": "https://www.geeksforgeeks.org/python-data-structures/",
  "chapter": "0001 Python",
  "content": null,
  "course": "industrial-training",
  "custom_content_copy": null,
  "docstatus": 0,
  "doctype": "Course Lesson",
  "file_type": "",
  "include_in_preview": 0,
  "index_label": null,
  "instructor_content": null,
  "instructor_notes": null,
  "modified": "2024-06-05 12:34:30.799658",
  "name": "0008 Data Structures (list, tuple, dict, sets)",
  "question": null,
  "quiz_id": null,
  "title": "Data Structures (list, tuple, dict, sets)",
  "youtube": null
 },
 {
  "body": "https://www.w3schools.com/python/python_classes.asp",
  "chapter": "0001 Python",
  "content": null,
  "course": "industrial-training",
  "custom_content_copy": null,
  "docstatus": 0,
  "doctype": "Course Lesson",
  "file_type": "",
  "include_in_preview": 1,
  "index_label": null,
  "instructor_content": null,
  "instructor_notes": null,
  "modified": "2024-06-05 12:35:08.815767",
  "name": "0009 Classes and Objects",
  "question": null,
  "quiz_id": null,
  "title": "Classes and Objects",
  "youtube": null
 },
 {
  "body": "https://www.w3schools.com/python/python_inheritance.asp",
  "chapter": "0001 Python",
  "content": null,
  "course": "industrial-training",
  "custom_content_copy": null,
  "docstatus": 0,
  "doctype": "Course Lesson",
  "file_type": "",
  "include_in_preview": 0,
  "index_label": null,
  "instructor_content": null,
  "instructor_notes": null,
  "modified": "2024-06-05 12:35:36.165096",
  "name": "0010 Inheriting a Class and its Object",
  "question": null,
  "quiz_id": null,
  "title": "Inheriting a Class and its Object",
  "youtube": null
 },
 {
  "body": "https://www.w3schools.com/python/python_inheritance.asp",
  "chapter": "0001 Python",
  "content": null,
  "course": "industrial-training",
  "custom_content_copy": null,
  "docstatus": 0,
  "doctype": "Course Lesson",
  "file_type": "",
  "include_in_preview": 1,
  "index_label": null,
  "instructor_content": null,
  "instructor_notes": null,
  "modified": "2024-06-05 12:36:05.062193",
  "name": "0011 Using Super in Classes",
  "question": null,
  "quiz_id": null,
  "title": "Using Super in Classes",
  "youtube": null
 },
 {
  "body": "https://wiki.nestorbird.com/wiki/how-to-use-monkey-patching-in-erpnext",
  "chapter": "0001 Python",
  "content": null,
  "course": "industrial-training",
  "custom_content_copy": null,
  "docstatus": 0,
  "doctype": "Course Lesson",
  "file_type": "",
  "include_in_preview": 1,
  "index_label": null,
  "instructor_content": null,
  "instructor_notes": null,
  "modified": "2024-06-05 12:36:43.374119",
  "name": "0012 Monkey Patching",
  "question": null,
  "quiz_id": null,
  "title": "Monkey Patching",
  "youtube": null
 },
 {
  "body": "https://www.geeksforgeeks.org/method-overriding-in-python/",
  "chapter": "0001 Python",
  "content": null,
  "course": "industrial-training",
  "custom_content_copy": null,
  "docstatus": 0,
  "doctype": "Course Lesson",
  "file_type": "",
  "include_in_preview": 1,
  "index_label": null,
  "instructor_content": null,
  "instructor_notes": null,
  "modified": "2024-06-05 12:37:53.347124",
  "name": "0013 Function Overriding",
  "question": null,
  "quiz_id": null,
  "title": "Function Overriding",
  "youtube": null
 },
 {
  "body": "https://www.w3schools.com/python/python_datatypes.asp",
  "chapter": "0001 Python",
  "content": null,
  "course": "industrial-training",
  "custom_content_copy": null,
  "docstatus": 0,
  "doctype": "Course Lesson",
  "file_type": "",
  "include_in_preview": 0,
  "index_label": null,
  "instructor_content": null,
  "instructor_notes": null,
  "modified": "2024-06-04 11:05:27.178022",
  "name": "0002 Data types",
  "question": null,
  "quiz_id": null,
  "title": "Data types",
  "youtube": null
 }
]